Workbook

Sheet MoSCoW Matrix
A1: Library Management System – MoSCoW Prioritisation
A2: Scoring: Impact (1-5) = value to users & stakeholders; Feasibility (1-5) = ease given time, budget, team. Priority Score = Impact x Feasibility (formula). Blue cells = judgement inputs you can change.
A4: ID | B4: Requirement | C4: Description | D4: Impact (1-5) | E4: Feasibility (1-5) | F4: Priority Score | G4: MoSCoW Category | H4: Impact Justification (Users & Stakeholders) | I4: Feasibility Justification (Time / Budget / Resources) | J4: Final Decision Rationale | K4: Target Release
A5: REQ-01 | B5: Search books by title and author | C5: Keyword search across catalogue by book title and author name. | D5: 5 | E5: 5 | F5: =D5*E5 -> 25 | G5: Must Have | H5: Every member and librarian uses it on every visit; without it the catalogue is unusable. | I5: Standard database query / indexed search; low effort, no third-party cost, 1 developer, 1 sprint. | J5: Highest value and lowest effort. Core function – system cannot launch without it. | K5: Release 1 (MVP)
A6: REQ-02 | B6: Online book reservation system | C6: Members reserve a book that is out/available and get a hold until pickup. | D6: 5 | E6: 4 | F6: =D6*E6 -> 20 | G6: Must Have | H6: Core library workflow; reduces queues and manual registers; directly serves members and librarians. | I6: Needs reservation table, status rules, expiry logic; moderate effort, no external cost. | J6: Essential to the library lifecycle (search > reserve > borrow). Needed for a usable MVP. | K6: Release 1 (MVP)
A7: REQ-03 | B7: Email notifications for overdue books | C7: Automatic emails on due-soon and overdue items. | D7: 4 | E7: 4 | F7: =D7*E7 -> 16 | G7: Must Have | H7: Protects library assets and fines revenue; reduces librarian manual follow-up; members avoid penalties. | I7: Scheduled job + SMTP/SendGrid free tier; low-moderate effort and cost. | J7: Overdue control is a core business need, and it is cheap to automate. Included in MVP. | K7: Release 1 (MVP)
A8: REQ-04 | B8: Monthly borrowing reports for administrators | C8: Auto-generated monthly report of borrowed books (exportable PDF/Excel). | D8: 4 | E8: 4 | F8: =D8*E8 -> 16 | G8: Should Have | H8: Administrators need it for stock and budget decisions, but the library can run without it at launch. | I8: Aggregation queries + export library; moderate effort once borrowing data exists. | J8: Important but depends on borrowing data from Must items. Can be delivered shortly after MVP. | K8: Release 2
A9: REQ-05 | B9: User-friendly dashboard for librarians | C9: Single screen showing issues, returns, overdue, reservations, quick actions. | D9: 4 | E9: 3 | F9: =D9*E9 -> 12 | G9: Should Have | H9: Improves librarian productivity and training time; high stakeholder satisfaction. | I9: Needs UX design and several widgets; moderate effort. Basic admin screens cover MVP. | J9: Valuable but MVP can use simple admin lists first; full dashboard follows. | K9: Release 2
A10: REQ-06 | B10: QR code scanning for borrowing and returning | C10: Scan book/member QR codes to issue and return books. | D10: 4 | E10: 3 | F10: =D10*E10 -> 12 | G10: Should Have | H10: Speeds up desk transactions and cuts data-entry errors. | I10: Needs QR generation, label printing and camera/scanner integration; moderate effort and some hardware cost. | J10: Big efficiency gain, but manual/ID entry works at launch. Schedule after core flows are stable. | K10: Release 2
A11: REQ-07 | B11: Users can review and rate books | C11: Star ratings and text reviews per book. | D11: 3 | E11: 4 | F11: =D11*E11 -> 12 | G11: Could Have | H11: Improves engagement and discovery but is not needed for lending operations. | I11: Simple CRUD plus moderation; low effort. | J11: Nice-to-have; add if time and budget remain after Must/Should items. | K11: Release 3
A12: REQ-08 | B12: Multi-language support | C12: UI available in multiple languages (e.g. English, Tamil, Hindi). | D12: 3 | E12: 3 | F12: =D12*E12 -> 9 | G12: Could Have | H12: Widens accessibility for diverse users; not critical if the primary user base shares one language. | I12: Requires i18n framework from the start and translation effort; moderate cost. | J12: Beneficial but not essential at launch. Build text with i18n keys so it can be added later cheaply. | K12: Release 3
A13: REQ-09 | B13: Chatbot for user assistance | C13: AI/FAQ chatbot answering member queries. | D13: 2 | E13: 2 | F13: =D13*E13 -> 4 | G13: Won't Have (this time) | H13: Convenient, but FAQs, search and librarian help cover the need. | I13: High effort: NLP/AI service, training content, ongoing cost and maintenance. | J13: Low impact for high cost. Deferred; revisit once usage data justifies it. | K13: Backlog / Future
A14: REQ-10 | B14: Mobile app version of the system | C14: Native iOS/Android app. | D14: 4 | E14: 1 | F14: =D14*E14 -> 4 | G14: Won't Have (this time) | H14: Useful for members, but a responsive website serves mobile users initially. | I14: Very high effort: separate codebases, app-store process, extra team and budget. | J14: Not feasible within current time/budget. Mitigation: make the web app mobile-responsive; plan app for a later phase. | K14: Backlog / Future
A16: Assumptions: small team (3-5 people), limited budget, ~3 releases; scores are team judgement and can be edited (blue cells). Category is chosen by judgement guided by Priority Score (>=16 Must, 12-15 Should, 9-11 Could, <9 Won't) with dependencies considered.

Sheet Summary
A1: MoSCoW Summary
A3: Category | B3: No. of Requirements | C3: Share of Total | D3: Requirements
A4: Must Have | B4: =COUNTIF('MoSCoW Matrix'!$G$5:$G$14,A4) -> 3 | C4: =B4/$B$8 -> 0.3 | D4: Search; Reservation; Overdue email alerts
A5: Should Have | B5: =COUNTIF('MoSCoW Matrix'!$G$5:$G$14,A5) -> 3 | C5: =B5/$B$8 -> 0.3 | D5: Monthly reports; Librarian dashboard; QR scanning
A6: Could Have | B6: =COUNTIF('MoSCoW Matrix'!$G$5:$G$14,A6) -> 2 | C6: =B6/$B$8 -> 0.2 | D6: Reviews & ratings; Multi-language
A7: Won't Have (this time) | B7: =COUNTIF('MoSCoW Matrix'!$G$5:$G$14,A7) -> 2 | C7: =B7/$B$8 -> 0.2 | D7: Chatbot; Mobile app (use responsive web)
A8: Total | B8: =SUM(B4:B7) -> 10 | C8: =SUM(C4:C7) -> 1

Sheet Jira Import
A1: Summary | B1: Issue Type | C1: Priority | D1: Labels | E1: Description | F1: Epic Name / Parent
A2: ='MoSCoW Matrix'!A5&" "&'MoSCoW Matrix'!B5 -> REQ-01 Search books by title and author | B2: Story | C2: =IF(LEFT('MoSCoW Matrix'!G5,4)="Must","Highest",IF(LEFT('MoSCoW Matrix'!G5,6)="Should","High",IF(LEFT('MoSCoW Matrix'!G5,5)="Could","Medium","Low"))) -> Highest | D2: =SUBSTITUTE(SUBSTITUTE(SUBSTITUTE(LEFT('MoSCoW Matrix'!G5,FIND(" ",'MoSCoW Matrix'!G5)-1),"Won't","Wont"),"Must","Must"),"Should","Should") -> Must | E2: ='MoSCoW Matrix'!C5&" | Rationale: "&'MoSCoW Matrix'!J5 -> Keyword search across catalogue by book title and author name. | Rationale: Highest value and lowest effort. Core function – system cannot launch without it. | F2: ='MoSCoW Matrix'!K5 -> Release 1 (MVP)
A3: ='MoSCoW Matrix'!A6&" "&'MoSCoW Matrix'!B6 -> REQ-02 Online book reservation system | B3: Story | C3: =IF(LEFT('MoSCoW Matrix'!G6,4)="Must","Highest",IF(LEFT('MoSCoW Matrix'!G6,6)="Should","High",IF(LEFT('MoSCoW Matrix'!G6,5)="Could","Medium","Low"))) -> Highest | D3: =SUBSTITUTE(SUBSTITUTE(SUBSTITUTE(LEFT('MoSCoW Matrix'!G6,FIND(" ",'MoSCoW Matrix'!G6)-1),"Won't","Wont"),"Must","Must"),"Should","Should") -> Must | E3: ='MoSCoW Matrix'!C6&" | Rationale: "&'MoSCoW Matrix'!J6 -> Members reserve a book that is out/available and get a hold until pickup. | Rationale: Essential to the library lifecycle (search > reserve > borrow). Needed for a usable MVP. | F3: ='MoSCoW Matrix'!K6 -> Release 1 (MVP)
A4: ='MoSCoW Matrix'!A7&" "&'MoSCoW Matrix'!B7 -> REQ-03 Email notifications for overdue books | B4: Story | C4: =IF(LEFT('MoSCoW Matrix'!G7,4)="Must","Highest",IF(LEFT('MoSCoW Matrix'!G7,6)="Should","High",IF(LEFT('MoSCoW Matrix'!G7,5)="Could","Medium","Low"))) -> Highest | D4: =SUBSTITUTE(SUBSTITUTE(SUBSTITUTE(LEFT('MoSCoW Matrix'!G7,FIND(" ",'MoSCoW Matrix'!G7)-1),"Won't","Wont"),"Must","Must"),"Should","Should") -> Must | E4: ='MoSCoW Matrix'!C7&" | Rationale: "&'MoSCoW Matrix'!J7 -> Automatic emails on due-soon and overdue items. | Rationale: Overdue control is a core business need, and it is cheap to automate. Included in MVP. | F4: ='MoSCoW Matrix'!K7 -> Release 1 (MVP)
A5: ='MoSCoW Matrix'!A8&" "&'MoSCoW Matrix'!B8 -> REQ-04 Monthly borrowing reports for administrators | B5: Story | C5: =IF(LEFT('MoSCoW Matrix'!G8,4)="Must","Highest",IF(LEFT('MoSCoW Matrix'!G8,6)="Should","High",IF(LEFT('MoSCoW Matrix'!G8,5)="Could","Medium","Low"))) -> High | D5: =SUBSTITUTE(SUBSTITUTE(SUBSTITUTE(LEFT('MoSCoW Matrix'!G8,FIND(" ",'MoSCoW Matrix'!G8)-1),"Won't","Wont"),"Must","Must"),"Should","Should") -> Should | E5: ='MoSCoW Matrix'!C8&" | Rationale: "&'MoSCoW Matrix'!J8 -> Auto-generated monthly report of borrowed books (exportable PDF/Excel). | Rationale: Important but depends on borrowing data from Must items. Can be delivered shortly after MVP. | F5: ='MoSCoW Matrix'!K8 -> Release 2
A6: ='MoSCoW Matrix'!A9&" "&'MoSCoW Matrix'!B9 -> REQ-05 User-friendly dashboard for librarians | B6: Story | C6: =IF(LEFT('MoSCoW Matrix'!G9,4)="Must","Highest",IF(LEFT('MoSCoW Matrix'!G9,6)="Should","High",IF(LEFT('MoSCoW Matrix'!G9,5)="Could","Medium","Low"))) -> High | D6: =SUBSTITUTE(SUBSTITUTE(SUBSTITUTE(LEFT('MoSCoW Matrix'!G9,FIND(" ",'MoSCoW Matrix'!G9)-1),"Won't","Wont"),"Must","Must"),"Should","Should") -> Should | E6: ='MoSCoW Matrix'!C9&" | Rationale: "&'MoSCoW Matrix'!J9 -> Single screen showing issues, returns, overdue, reservations, quick actions. | Rationale: Valuable but MVP can use simple admin lists first; full dashboard follows. | F6: ='MoSCoW Matrix'!K9 -> Release 2
A7: ='MoSCoW Matrix'!A10&" "&'MoSCoW Matrix'!B10 -> REQ-06 QR code scanning for borrowing and returning | B7: Story | C7: =IF(LEFT('MoSCoW Matrix'!G10,4)="Must","Highest",IF(LEFT('MoSCoW Matrix'!G10,6)="Should","High",IF(LEFT('MoSCoW Matrix'!G10,5)="Could","Medium","Low"))) -> High | D7: =SUBSTITUTE(SUBSTITUTE(SUBSTITUTE(LEFT('MoSCoW Matrix'!G10,FIND(" ",'MoSCoW Matrix'!G10)-1),"Won't","Wont"),"Must","Must"),"Should","Should") -> Should | E7: ='MoSCoW Matrix'!C10&" | Rationale: "&'MoSCoW Matrix'!J10 -> Scan book/member QR codes to issue and return books. | Rationale: Big efficiency gain, but manual/ID entry works at launch. Schedule after core flows are stable. | F7: ='MoSCoW Matrix'!K10 -> Release 2
A8: ='MoSCoW Matrix'!A11&" "&'MoSCoW Matrix'!B11 -> REQ-07 Users can review and rate books | B8: Story | C8: =IF(LEFT('MoSCoW Matrix'!G11,4)="Must","Highest",IF(LEFT('MoSCoW Matrix'!G11,6)="Should","High",IF(LEFT('MoSCoW Matrix'!G11,5)="Could","Medium","Low"))) -> Medium | D8: =SUBSTITUTE(SUBSTITUTE(SUBSTITUTE(LEFT('MoSCoW Matrix'!G11,FIND(" ",'MoSCoW Matrix'!G11)-1),"Won't","Wont"),"Must","Must"),"Should","Should") -> Could | E8: ='MoSCoW Matrix'!C11&" | Rationale: "&'MoSCoW Matrix'!J11 -> Star ratings and text reviews per book. | Rationale: Nice-to-have; add if time and budget remain after Must/Should items. | F8: ='MoSCoW Matrix'!K11 -> Release 3
A9: ='MoSCoW Matrix'!A12&" "&'MoSCoW Matrix'!B12 -> REQ-08 Multi-language support | B9: Story | C9: =IF(LEFT('MoSCoW Matrix'!G12,4)="Must","Highest",IF(LEFT('MoSCoW Matrix'!G12,6)="Should","High",IF(LEFT('MoSCoW Matrix'!G12,5)="Could","Medium","Low"))) -> Medium | D9: =SUBSTITUTE(SUBSTITUTE(SUBSTITUTE(LEFT('MoSCoW Matrix'!G12,FIND(" ",'MoSCoW Matrix'!G12)-1),"Won't","Wont"),"Must","Must"),"Should","Should") -> Could | E9: ='MoSCoW Matrix'!C12&" | Rationale: "&'MoSCoW Matrix'!J12 -> UI available in multiple languages (e.g. English, Tamil, Hindi). | Rationale: Beneficial but not essential at launch. Build text with i18n keys so it can be added later cheaply. | F9: ='MoSCoW Matrix'!K12 -> Release 3
A10: ='MoSCoW Matrix'!A13&" "&'MoSCoW Matrix'!B13 -> REQ-09 Chatbot for user assistance | B10: Story | C10: =IF(LEFT('MoSCoW Matrix'!G13,4)="Must","Highest",IF(LEFT('MoSCoW Matrix'!G13,6)="Should","High",IF(LEFT('MoSCoW Matrix'!G13,5)="Could","Medium","Low"))) -> Low | D10: =SUBSTITUTE(SUBSTITUTE(SUBSTITUTE(LEFT('MoSCoW Matrix'!G13,FIND(" ",'MoSCoW Matrix'!G13)-1),"Won't","Wont"),"Must","Must"),"Should","Should") -> Wont | E10: ='MoSCoW Matrix'!C13&" | Rationale: "&'MoSCoW Matrix'!J13 -> AI/FAQ chatbot answering member queries. | Rationale: Low impact for high cost. Deferred; revisit once usage data justifies it. | F10: ='MoSCoW Matrix'!K13 -> Backlog / Future
A11: ='MoSCoW Matrix'!A14&" "&'MoSCoW Matrix'!B14 -> REQ-10 Mobile app version of the system | B11: Story | C11: =IF(LEFT('MoSCoW Matrix'!G14,4)="Must","Highest",IF(LEFT('MoSCoW Matrix'!G14,6)="Should","High",IF(LEFT('MoSCoW Matrix'!G14,5)="Could","Medium","Low"))) -> Low | D11: =SUBSTITUTE(SUBSTITUTE(SUBSTITUTE(LEFT('MoSCoW Matrix'!G14,FIND(" ",'MoSCoW Matrix'!G14)-1),"Won't","Wont"),"Must","Must"),"Should","Should") -> Wont | E11: ='MoSCoW Matrix'!C14&" | Rationale: "&'MoSCoW Matrix'!J14 -> Native iOS/Android app. | Rationale: Not feasible within current time/budget. Mitigation: make the web app mobile-responsive; plan app for a later phase. | F11: ='MoSCoW Matrix'!K14 -> Backlog / Future
A13: Use: File > Save As CSV from this sheet, then import in Jira (see steps). Labels are Must / Should / Could / Wont (Jira labels cannot contain spaces or apostrophes).
